setup.py
amp/__init__.py
amp/apps.py
amp/context_processors.py
amp/middleware/__init__.py
amp/middleware/amp.py
amp/templatetags/__init__.py
amp/templatetags/amp_tags.py
django_amp.egg-info/PKG-INFO
django_amp.egg-info/SOURCES.txt
django_amp.egg-info/dependency_links.txt
django_amp.egg-info/not-zip-safe
django_amp.egg-info/top_level.txt