Metadata-Version: 1.1
Name: django-amp
Version: 1.0.a2
Summary: A small toolset for rendering Google AMP pages for Django projects
Home-page: http://github.com/blturner/django-amp
Author: Benjamin Turner
Author-email: benturn@gmail.com
License: MIT
Download-URL: https://github.com/blturner/django-amp/archive/v1.0.a2.tar.gz
Platform: UNKNOWN
